facets/.gitignore
facets/AUTHORS
facets/CONTRIBUTING.md
facets/CONTRIBUTORS
facets/LICENSE
facets/README.md
facets/WORKSPACE
facets/__init__.py
facets/colab_facets.ipynb
facets/facets/BUILD
facets/facets/visualizations.html
facets/facets-dist/facets-jupyter.html
facets/facets_atlasmaker/.gitignore
facets/facets_atlasmaker/BUILD
facets/facets_atlasmaker/README.md
facets/facets_atlasmaker/atlasmaker.py
facets/facets_atlasmaker/atlasmaker_io.py
facets/facets_atlasmaker/atlasmaker_io_test.py
facets/facets_atlasmaker/convert.py
facets/facets_atlasmaker/convert_test.py
facets/facets_atlasmaker/montage.py
facets/facets_atlasmaker/montage_test.py
facets/facets_atlasmaker/parallelize.py
facets/facets_atlasmaker/parallelize_test.py
facets/facets_atlasmaker/pylintrc
facets/facets_atlasmaker/requirements.txt
facets/facets_atlasmaker/testdata/Googleplex-Patio-Aug-2014.JPG
facets/facets_atlasmaker/testdata/attributions.txt
facets/facets_atlasmaker/testdata/testfiles_smalllist.csv
facets/facets_atlasmaker/testdata/testfiles_smalllist_with_dups.csv
facets/facets_atlasmaker/testdata/wikipedia_images_16.csv
facets/facets_atlasmaker/utils/BUILD
facets/facets_atlasmaker/utils/README.md
facets/facets_atlasmaker/utils/wikipedia_sourcelist_generator.py
facets/facets_atlasmaker/utils/wikipedia_sourcelist_generator_test.py
facets/facets_dive/Dive_demo.ipynb
facets/facets_dive/README.md
facets/facets_dive/components/facets_dive/BUILD
facets/facets_dive/components/facets_dive/facets-dive.html
facets/facets_dive/components/facets_dive/facets-dive.ts
facets/facets_dive/components/facets_dive/test.html
facets/facets_dive/components/facets_dive/test.ts
facets/facets_dive/components/facets_dive_controls/BUILD
facets/facets_dive/components/facets_dive_controls/facets-dive-controls.html
facets/facets_dive/components/facets_dive_controls/facets-dive-controls.ts
facets/facets_dive/components/facets_dive_controls/test.html
facets/facets_dive/components/facets_dive_controls/test.ts
facetswrapper-0.1.dist-info/LICENSE.txt
facetswrapper-0.1.dist-info/METADATA
facetswrapper-0.1.dist-info/WHEEL
facetswrapper-0.1.dist-info/top_level.txt
facetswrapper-0.1.dist-info/RECORD
