Metadata-Version: 2.1
Name: facetswrapper
Version: 0.1
Summary: A wrapper for the Facets project (https://pair-code.github.io/facets/).
Home-page: https://gitlab.com/sivan.altinakar/facetswrapper
Author: Sivan Altinakar
Author-email: sivan.altinakar@gmail.com
License: UNKNOWN
Project-URL: Documentation, https://gitlab.com/sivan.altinakar/facetswrapper/blob/master/README.md
Project-URL: Source, https://gitlab.com/sivan.altinakar/facetswrapper
Keywords: dataviz data_visualization wrapper
Platform: UNKNOWN
Classifier: Development Status :: 4 - Beta
Classifier: Intended Audience :: Science/Research
Classifier: License :: OSI Approved :: Apache Software License
Classifier: Natural Language :: English
Classifier: Programming Language :: Python :: 3
Classifier: Topic :: Scientific/Engineering :: Visualization
Requires-Python: >=3.6
Requires-Dist: pandas
Requires-Dist: protobuf
Provides-Extra: test
